AUTHORS.rst
LICENSE
MANIFEST.in
README.rst
buildout.cfg
develop.cfg
pyproject.toml
requirements.txt
setup.py
version.txt
beat/__init__.py
beat.core.egg-info/PKG-INFO
beat.core.egg-info/SOURCES.txt
beat.core.egg-info/dependency_links.txt
beat.core.egg-info/entry_points.txt
beat.core.egg-info/not-zip-safe
beat.core.egg-info/requires.txt
beat.core.egg-info/top_level.txt
beat/core/__init__.py
beat/core/algorithm.py
beat/core/baseformat.py
beat/core/data.py
beat/core/data_loaders.py
beat/core/database.py
beat/core/dataformat.py
beat/core/dock.py
beat/core/drawing.py
beat/core/environments.py
beat/core/experiment.py
beat/core/hash.py
beat/core/inputs.py
beat/core/library.py
beat/core/loader.py
beat/core/outputs.py
beat/core/plotter.py
beat/core/plotterparameter.py
beat/core/protocoltemplate.py
beat/core/stats.py
beat/core/toolchain.py
beat/core/utils.py
beat/core/version.py
beat/core/worker.py
beat/core/bcp/__init__.py
beat/core/bcp/broker.py
beat/core/bcp/worker.py
beat/core/bcpapi/BCP.py
beat/core/bcpapi/__init__.py
beat/core/bcpapi/broker.py
beat/core/bcpapi/client.py
beat/core/bcpapi/execution.py
beat/core/bcpapi/processor.py
beat/core/bcpapi/worker.py
beat/core/bcpapi/zhelpers.py
beat/core/execution/__init__.py
beat/core/execution/base.py
beat/core/execution/docker.py
beat/core/execution/local.py
beat/core/execution/remote.py
beat/core/execution/subprocess.py
beat/core/prototypes/__init__.py
beat/core/prototypes/algorithm.json
beat/core/prototypes/algorithm.py
beat/core/prototypes/database.json
beat/core/prototypes/database.py
beat/core/prototypes/dataformat.json
beat/core/prototypes/library.json
beat/core/prototypes/library.py
beat/core/prototypes/plotter.json
beat/core/prototypes/plotter.py
beat/core/prototypes/plotterparameter.json
beat/core/prototypes/protocoltemplate.json
beat/core/prototypes/statistics.json
beat/core/prototypes/toolchain.json
beat/core/schema/__init__.py
beat/core/schema/algorithm/1.json
beat/core/schema/algorithm/2.json
beat/core/schema/algorithm/3.json
beat/core/schema/algorithm/common.json
beat/core/schema/common/1.json
beat/core/schema/database/1.json
beat/core/schema/database/2.json
beat/core/schema/database/common.json
beat/core/schema/dataformat/1.json
